autoqtl/__init__.py
autoqtl/autoqtl.py
autoqtl/base.py
autoqtl/decorators.py
autoqtl/export_utils.py
autoqtl/gp_deap.py
autoqtl/gp_types.py
autoqtl/operator_utils.py
autoqtl/builtins/__init__.py
autoqtl/builtins/combine_dfs.py
autoqtl/builtins/feature_encoding_frequency_selector.py
autoqtl/builtins/genetic_encoders.py
autoqtl/config/__init__.py
autoqtl/config/regressor.py
autoqtl-0.1.1a0.dist-info/LICENSE
autoqtl-0.1.1a0.dist-info/METADATA
autoqtl-0.1.1a0.dist-info/WHEEL
autoqtl-0.1.1a0.dist-info/entry_points.txt
autoqtl-0.1.1a0.dist-info/top_level.txt
autoqtl-0.1.1a0.dist-info/zip-safe
autoqtl-0.1.1a0.dist-info/RECORD
