Metadata-Version: 2.1
Name: autoqtl
Version: 0.1.1a0
Summary: Automated Quantitative Trait Locus Analysis Tool
Home-page: https://github.com/EpistasisLab/autoqtl
Author: Attri Ghosh
Author-email: attri.ghosh@cshs.org
License: GNU/LGPLv3
Keywords: qtl analysis,pipeline optimization,hyperparameter optimization,data science,genetic programming,evolutionary computation
Classifier: Intended Audience :: Science/Research
Classifier: License :: OSI Approved :: GNU Lesser General Public License v3 (LGPLv3)
Classifier: Programming Language :: Python :: 3.9
Classifier: Programming Language :: Python :: 3.10
Classifier: Topic :: Scientific/Engineering :: Artificial Intelligence
License-File: LICENSE
Requires-Dist: numpy >=1.16.3
Requires-Dist: scipy >=1.3.1
Requires-Dist: scikit-learn ==1.2.2
Requires-Dist: deap >=1.2
Requires-Dist: update-checker >=0.16
Requires-Dist: tqdm >=4.36.1
Requires-Dist: stopit >=1.1.1
Requires-Dist: pandas >=0.24.2
Requires-Dist: joblib >=0.13.2
Requires-Dist: matplotlib >=3.6.2
Requires-Dist: seaborn >=0.11.2
Requires-Dist: shap >=0.39.0
Requires-Dist: fpdf >=1.7.2
Requires-Dist: filelock >=3.11.0
Provides-Extra: imblearn
Requires-Dist: imbalanced-learn >=0.7.0 ; extra == 'imblearn'
Provides-Extra: mdr
Requires-Dist: scikit-mdr >=0.4.4 ; extra == 'mdr'
Provides-Extra: skrebate
Requires-Dist: skrebate >=0.3.4 ; extra == 'skrebate'
